cdir-1.3.data/scripts/cdir.cmd
cdir-1.3.data/scripts/cdir.ps1
cdir-1.3.data/scripts/cdir.sh
cdir_cli/__init__.py
cdir_cli/__main__.py
cdir_cli/data/__init__.py
cdir_cli/data/file_writer.py
cdir_cli/data/folder_navigator.py
cdir_cli/data/script_writer.py
cdir_cli/user_interface/__init__.py
cdir_cli/user_interface/cursor.py
cdir_cli/user_interface/key_press_handler.py
cdir_cli/user_interface/key_press_listener.py
cdir_cli/user_interface/main_view.py
cdir_cli/user_interface/query.py
cdir_cli/user_interface/scroll_position.py
cdir_cli/user_interface/ui.py
cdir-1.3.dist-info/LICENSE
cdir-1.3.dist-info/METADATA
cdir-1.3.dist-info/WHEEL
cdir-1.3.dist-info/entry_points.txt
cdir-1.3.dist-info/top_level.txt
cdir-1.3.dist-info/RECORD
