Metadata-Version: 2.1
Name: cdir
Version: 1.3
Summary: A faster way to navigate folders and browse files in Windows and Linux shells.
Home-page: https://github.com/EskelinenAntti/cdir
Author: Antti Eskelinen
Author-email: antti.eskelinen3@gmail.com
License: UNKNOWN
Platform: UNKNOWN
Classifier: Programming Language :: Python :: 3
Classifier: License :: OSI Approved :: MIT License
Classifier: Operating System :: OS Independent
Requires-Dist: windows-curses (>=2.1.0) ; platform_system == "Windows"
